MANIFEST.in
README.rst
setup.py
c/CMakeLists.txt
c/triangle.c
c/triangle.h
c/tricall.c
tribad/__init__.py
tribad/c_triangle.pxd
tribad/core.pyx
tribad/plot.py
tribad/version.py
tribad.egg-info/PKG-INFO
tribad.egg-info/SOURCES.txt
tribad.egg-info/dependency_links.txt
tribad.egg-info/requires.txt
tribad.egg-info/top_level.txt
tribad/data/A.1.ele
tribad/data/A.1.node
tribad/data/A.1.poly
tribad/data/A.poly
tribad/data/bbox.1.area
tribad/data/bbox.1.ele
tribad/data/bbox.1.node
tribad/data/box.1.ele
tribad/data/box.1.node
tribad/data/box.1.poly
tribad/data/box.2.ele
tribad/data/box.2.node
tribad/data/box.2.poly
tribad/data/box.3.ele
tribad/data/box.3.node
tribad/data/box.3.poly
tribad/data/box.4.ele
tribad/data/box.4.node
tribad/data/box.4.poly
tribad/data/box.poly
tribad/data/diamond_02_00009.1.ele
tribad/data/diamond_02_00009.1.node
tribad/data/diamond_02_00009.1.v.edge
tribad/data/diamond_02_00009.1.v.node
tribad/data/diamond_02_00009.node
tribad/data/dots.1.v.edge
tribad/data/dots.1.v.node
tribad/data/dots.node
tribad/data/double_hex.1.ele
tribad/data/double_hex.1.node
tribad/data/double_hex.1.poly
tribad/data/double_hex.2.ele
tribad/data/double_hex.2.node
tribad/data/double_hex.2.poly
tribad/data/double_hex.poly
tribad/data/double_hex2.1.ele
tribad/data/double_hex2.1.node
tribad/data/double_hex2.1.poly
tribad/data/double_hex2.2.ele
tribad/data/double_hex2.2.node
tribad/data/double_hex2.2.poly
tribad/data/double_hex2.poly
tribad/data/double_hex3.1.ele
tribad/data/double_hex3.1.node
tribad/data/double_hex3.1.poly
tribad/data/double_hex3.node
tribad/data/double_hex3.poly
tribad/data/ell.ele
tribad/data/ell.node
tribad/data/face.1.ele
tribad/data/face.1.node
tribad/data/face.1.poly
tribad/data/face.poly
tribad/data/greenland.ele
tribad/data/greenland.node
tribad/data/la.1.ele
tribad/data/la.1.node
tribad/data/la.1.poly
tribad/data/la.poly
tribad/data/spiral.1.ele
tribad/data/spiral.1.node
tribad/data/spiral.node
tribad/data/spiral.q.1.ele
tribad/data/spiral.q.1.node
tribad/data/spiral.r.1.ele
tribad/data/spiral.r.1.node
tribad/data/square_circle_hole.1.ele
tribad/data/square_circle_hole.1.node
