Metadata-Version: 1.1
Name: tribad
Version: 20190722
Summary: Python binding to the triangle library
Home-page: http://dzhelil.info/triangle
Author: Dzhelil Rufat
Author-email: drufat@caltech.edu
License: GNU LGPL
Platform: UNKNOWN
Classifier: Development Status :: 4 - Beta
Classifier: Programming Language :: Python :: 2.6
Classifier: Programming Language :: Python :: 2.7
Classifier: Programming Language :: Python :: 3.2
Classifier: Programming Language :: Python :: 3.3
Classifier: Programming Language :: Python :: 3.4
Classifier: Programming Language :: Python :: 3.5
Classifier: Programming Language :: Python :: 3.6
